inlinehashes/__init__.py
inlinehashes/app.py
inlinehashes/lib.py
inlinehashes-0.0.5.dist-info/entry_points.txt
inlinehashes-0.0.5.dist-info/METADATA
inlinehashes-0.0.5.dist-info/WHEEL
inlinehashes-0.0.5.dist-info/LICENSE
inlinehashes-0.0.5.dist-info/RECORD
