Metadata-Version: 2.1
Name: inlinehashes
Version: 0.0.5
Summary: Hash generator for HTML inline styles and scripts
Home-page: https://github.com/dethos/inlinehashes
License: MIT
Author: Gonçalo Valério
Author-email: gon@ovalerio.net
Requires-Python: >=3.11,<4.0
Classifier: Development Status :: 3 - Alpha
Classifier: Environment :: Console
Classifier: Intended Audience :: Developers
Classifier: License :: OSI Approved :: MIT License
Classifier: Programming Language :: Python :: 3
Classifier: Programming Language :: Python :: 3.11
Classifier: Programming Language :: Python :: 3.11
Classifier: Topic :: Security
Classifier: Topic :: Text Processing :: Markup :: HTML
Classifier: Typing :: Typed
Requires-Dist: beautifulsoup4 (>=4.10.0,<5.0.0)
Requires-Dist: rich (>=13.2.0,<14.0.0)
Project-URL: Repository, https://github.com/dethos/inlinehashes
